unreal_qt/__init__.py
unreal_qt/dark_bar.py
unreal_qt-0.0.3.dist-info/licenses/LICENSE
unreal_qt-0.0.3.dist-info/METADATA
unreal_qt-0.0.3.dist-info/WHEEL
unreal_qt-0.0.3.dist-info/top_level.txt
unreal_qt-0.0.3.dist-info/RECORD
